automatically_change_wallpaper/__init__.py
automatically_change_wallpaper/change_background.py
automatically_change_wallpaper/main.py
automatically_change_wallpaper/save_frame.py
automatically_change_wallpaper-1.4.dist-info/LICENSE.md
automatically_change_wallpaper-1.4.dist-info/METADATA
automatically_change_wallpaper-1.4.dist-info/WHEEL
automatically_change_wallpaper-1.4.dist-info/entry_points.txt
automatically_change_wallpaper-1.4.dist-info/top_level.txt
automatically_change_wallpaper-1.4.dist-info/RECORD
