Metadata-Version: 2.1
Name: automatically_change_wallpaper
Version: 1.4
License-File: LICENSE.md
